[
  {
    "name": "凪",
    "message": "「你好！」"
  },
  {
    "message": "没有特别的紧张，堂堂正正地出现在对方面前。"
  },
  {
    "name": "声のデカい男子学生",
    "message": "「什么！？你是谁啊！」"
  },
  {
    "message": "依然是声音洪亮的男孩。在明显的反应中，无礼地接近他们。"
  },
  {
    "name": "凪",
    "message": "「哎呀，我刚刚在角落里睡着了，不知不觉就有人来了呢」"
  },
  {
    "name": "凪",
    "message": "「啊，外面已经暗下来了啊……那么，晚上好吧？」"
  },
  {
    "name": "凪",
    "message": "「晚上好！」"
  },
  {
    "name": "声のデカい男子学生",
    "message": "「闭嘴啊你！！」"
  },
  {
    "message": "对你这样的人，花是不会说这样的话的。"
  },
  {
    "message": "以成熟的态度去接近他们，轻轻拍了拍粗鲁的男学生的肩膀。"
  },
  {
    "name": "凪",
    "message": "「对了，你们几位在做什么呢？」"
  },
  {
    "name": "凪",
    "message": "「难道是在抢劫？那边躺着的人看起来很痛苦呢」"
  },
  {
    "message": "小胖孩仍然蜷缩着，低着头。"
  },
  {
    "name": "声のデカい男子学生",
    "message": "「啊啊……」"
  },
  {
    "name": "がさつな男子学生",
    "message": "「你这家伙……别太嚣张了。想遭殃吗？」"
  },
  {
    "message": "我用手拍了拍他的肩膀，却被粗暴地甩开，只能无奈地耸耸肩。"
  },
  {
    "name": "凪",
    "message": "「那可不行。刚入学就被欺负可不是什么好事啊」"
  },
  {
    "name": "龍司",
    "message": "「刚入学……？」"
  },
  {
    "name": "龍司",
    "message": "「啊，原来你就是那个中奖的人啊」"
  },
  {
    "name": "龍司",
    "message": "「你是珠贺良区的垃圾吧？我知道的，哈哈哈」"
  },
  {
    "message": "直接这样说出来……"
  },
  {
    "message": "不过我可不是会上当受骗的傻瓜。"
  },
  {
    "name": "凪",
    "message": "「既然你知道了，那就更好说了。从明天开始，不，从今天开始就请多多关照吧！」"
  },
  {
    "name": "声のデカい男子学生",
    "message": "「这家伙，一脸轻松的样子……我要让他知道自己的处境！」"
  },
  {
    "name": "凪",
    "message": "「哎呀！」"
  },
  {
    "message": "果断地向前走去，轻松避开了挥舞的拳头。"
  },
  {
    "message": "穿梭而过，迅速冲到了目标人物面前。"
  },
  {
    "name": "凪",
    "message": "「嗨，你是龙司对吧？」"
  },
  {
    "name": "龍司",
    "message": "「……」"
  },
  {
    "name": "凪",
    "message": "「要不要聊聊？」"
  },
  {
    "name": "龍司",
    "message": "「聊什么？」"
  },
  {
    "name": "凪",
    "message": "「从那个滚在地上的小胖孩那里抢钱，还让声音大的手下去打他，看起来你玩得很high啊。」"
  },
  {
    "name": "凪",
    "message": "「这说明你已经很有经验了。这不是你第一次做这种事吧？」"
  },
  {
    "name": "凪",
    "message": "「我不想被牵扯进去，所以就当什么都没看见吧。今天就散伙吧。」"
  },
  {
    "name": "龍司",
    "message": "「哈哈！你真有意思。这种事不是你这样的人能决定的。」"
  },
  {
    "name": "凪",
    "message": "「不过，那边也有目击者在，对你们来说也很麻烦吧？」"
  },
  {
    "name": "龍司",
    "message": "「谁会相信珠贺良区的人的话呢。」"
  },
  {
    "name": "凪",
    "message": "「那就让我来调查一下吧。这对今后的学生生活也很有帮助。」"
  },
  {
    "name": "凪",
    "message": "「那么，你打算怎么办？」"
  },
  {
    "name": "龍司",
    "message": "「……」"
  },
  {
    "message": "大家都没有认真交谈的意愿，所以只能互相瞪视。"
  },
  {
    "message": "顺便说一下，我可不擅长打架之类的。"
  },
  {
    "message": "师傅说我虽然动作很一流，但力气却是超级三流，完全没有天赋。"
  },
  {
    "message": "不过，总有办法解决的吧？我们不必正面对抗，总有其他方法。"
  },
  {
    "message": "这次也是这样想的，要好好和龙司谈谈。"
  },
  {
    "name": "龍司",
    "message": "「哼……」"
  },
  {
    "name": "龍司",
    "message": "「我兴致都没了，走了。」"
  },
  {
    "name": "声のデカい男子学生",
    "message": "「可以吗！？这家伙要是不说话，谁知道他会不会做些什么！？最好好好教训他一顿……」"
  },
  {
    "name": "龍司",
    "message": "「你这个白痴。要是没有决定性的证据，谁会相信这种垃圾的话呢。」"
  },
  {
    "name": "凪",
    "message": "「证据？也许真的有呢？」"
  },
  {
    "name": "龍司",
    "message": "「那你就应该拿着所谓的证据来威胁我们啊。」"
  },
  {
    "name": "龍司",
    "message": "「哼……即便真的有什么证据，我也会把它彻底压下去。我会采取一切手段。」"
  },
  {
    "message": "一切手段吗……这家伙果然很狠啊。"
  },
  {
    "name": "凪",
    "message": "「究竟是真是假，明天就知道了。」"
  },
  {
    "name": "がさつな男子学生",
    "message": "「……你这个混蛋！」"
  },
  {
    "name": "龍司",
    "message": "「算了吧，走了。」"
  },
  {
    "message": "被遗弃的围观群众急忙走出了外面。"
  },
  {
    "message": "他一边炫耀自己的地位，一边离开，我只能挠挠头。"
  },
  {
    "message": "看来比我想象的还要棘手。希望今后不要再有什么牵扯了……。"
  },
  {
    "name": "凪",
    "message": "「喂，没事吧？」"
  },
  {
    "message": "也许是因为疼痛而恍惚了，听到呼唤后小胖孩猛地抬起头，站了起来。"
  },
  {
    "name": "小太り君",
    "message": "「难、难道是你为了救我而出来的吗？」"
  },
  {
    "name": "凪",
    "message": "「也不是那样子的……」"
  },
  {
    "name": "凪",
    "message": "「不，也对，我看着情况果然如此发展了。」"
  },
  {
    "name": "凪",
    "message": "（这样说比较方便）"
  },
  {
    "name": "凪",
    "message": "「不过，更重要的是你的问题。」"
  },
  {
    "name": "凪",
    "message": "「这到底是怎么回事呢？」"
  },
  {
    "message": "我举起手中的东西，小胖孩睁大眼睛，似乎很感兴趣。"
  },
  {
    "name": "小太り君",
    "message": "「那、那难道是……！」"
  },
  {
    "name": "凪",
    "message": "「你之前交给那些人的信封，里面应该是钱吧。」"
  },
  {
    "name": "凪",
    "message": "「真是个白痴！看来是被吓到了，所以落下了。」"
  },
  {
    "name": "凪",
    "message": "「正好，就让我来还给你吧。没问题吧？」"
  },
  {
    "name": "小太り君",
    "message": "「嗯……是这样的……」"
  },
  {
    "name": "凪",
    "message": "「顺便的话，如果能得到一些报酬就更好了。」"
  },
  {
    "name": "小太り君",
    "message": "「那、那就请收下吧……」"
  },
  {
    "message": "小胖孩还没从惊讶中反应过来，目瞪口呆的。"
  },
  {
    "message": "其实，钱掉落完全是个意外，我只是顺手拿回来的，不过没必要特意说明。"
  },
  {
    "message": "我趁小胖孩平静下来的时候，也看了看角落里蓼科藏着的地方，但是没有任何动静。"
  },
  {
    "name": "小太り君",
    "message": "「那个……谢谢你。」"
  },
  {
    "name": "凪",
    "message": "「没事，不过你，不是一直被敲诈吗？」"
  },
  {
    "name": "凪",
    "message": "「找人说一说，看看能不能帮帮你也行吧？」"
  },
  {
    "name": "小太り君",
    "message": "「学生的事，由学生自己解决，这就是这所学校的道理……」"
  },
  {
    "name": "小太り君",
    "message": "「而且龙司君如果一直说下去，相信他也会意识到这样做是不对的」"
  },
  {
    "name": "凪",
    "message": "「……你是不是太相信人了？」"
  },
  {
    "name": "凪",
    "message": "「那种人一旦尝到甜头，不管用什么方法都会一次次重复下去，直到遭到痛苦的教训为止」"
  },
  {
    "message": "小胖孩不安地四处张望，但还是摇了摇头。"
  },
  {
    "name": "小太り君",
    "message": "「他从一年级开始就是这样了，不是从那时候就开始了。他虽然很自负，但是很认真地在努力」"
  },
  {
    "name": "小太り君",
    "message": "「但是到了二年级，加入了学生会之后……」"
  },
  {
    "name": "凪",
    "message": "「学生会……？」"
  },
  {
    "name": "小太り君",
    "message": "「他是风纪委员长，围绕在他周围的人，也都是作为助手在跟随着他」"
  },
  {
    "message": "看来，那家伙的地位比想象中还要高。"
  },
  {
    "name": "凪",
    "message": "「唔……」"
  },
  {
    "message": "我好像听说过关于学生会的事。"
  },
  {
    "name": "凪",
    "message": "「虽然有点不太好的预感，不过算了吧。」"
  },
  {
    "message": "如果再深思下去也无济于事，不如把注意力转移到别的地方比较好。"
  },
  {
    "name": "凪",
    "message": "「以前是善良的人，但后来因为某些原因变成了坏人，这种事情也很常见。」"
  },
  {
    "name": "凪",
    "message": "「要是不及时采取行动，自己反而会遭殃吃亏。」"
  },
  {
    "name": "小太り君",
    "message": "「嗯……我知道，但是……」"
  },
  {
    "name": "小太り君",
    "message": "「不过我还是相信龙司君，因为他是我的朋友。」"
  },
  {
    "name": "小太り君",
    "message": "「对不起。」"
  },
  {
    "name": "凪",
    "message": "「没什么好道歉的。」"
  },
  {
    "name": "小太り君",
    "message": "「啊，是这样啊。」"
  },
  {
    "name": "小太り君",
    "message": "「那个……你为什么对我这个素不相识的人这么好呢？」"
  },
  {
    "name": "凪",
    "message": "「我不是在对你好，只是稍微有点担心而已。」"
  },
  {
    "message": "太过善良有时也会成为不幸的根源。"
  },
  {
    "message": "有人为了善意而担保借款，结果陷入了多重债务，如今在珠贺良区生活。"
  },
  {
    "message": "不过……每个人的选择都是自由的，我是这么认为的。"
  },
  {
    "message": "我觉得不应该再多说什么了，于是轻轻拍了拍手。"
  },
  {
    "name": "凪",
    "message": "「好了，没必要久留，说不定他会发现钱丢了就回来呢。」"
  },
  {
    "name": "小太り君",
    "message": "「谢谢你的帮助，我都不知道你的名字。」"
  },
  {
    "name": "小太り君",
    "message": "「不过我们最好不要再有什么来往了。」"
  },
  {
    "name": "小太り君",
    "message": "「我……很软弱，无论我有多大的决心，都无法做到。」"
  },
  {
    "name": "小太り君",
    "message": "「不，还是对不起。那么再见。」"
  },
  {
    "message": "说完这番话，小胖孩就朝着出口跑了出去。"
  },
  {
    "name": "凪",
    "message": "「也不用他说，我本来就不想和他扯上什么关系。」"
  },
  {
    "message": "我仰头望向天花板，嘟囔着。"
  },
  {
    "message": "我介入这件欺负事件，命运就已经注定了。"
  },
  {
    "message": "我只能祈祷那所谓的神明，不要让这件事变得更麻烦。"
  },
  {
    "name": "凪",
    "message": "「那么，蓼科呢……」"
  },
  {
    "message": "就在我准备去关注那个导致这件事发生的人物时。"
  },
  {
    "message": "我注意到本应该离开储藏室的小胖孩，却在出口附近不自然地停了下来。"
  },
  {
    "name": "凪",
    "message": "「怎么了，难道那些人又回来了吗？」"
  },
  {
    "message": "我走近一看，他正在局促不安地动来动去。"
  },
  {
    "name": "小太り君",
    "message": "「那个……呃……」"
  },
  {
    "message": "他支支吾吾，不停地挪动着身体。"
  },
  {
    "name": "凪",
    "message": "「……你这种动作，有点让人觉得恶心啊。」"
  },
  {
    "name": "小太り君",
    "message": "「可是……」"
  },
  {
    "message": "他一直偷偷地看向门口，我好奇地伸手去拉门。"
  },
  {
    "name": "ファイブ",
    "message": "「……………………」"
  },
  {
    "name": "凪",
    "message": "「……………………」"
  },
  {
    "name": "小太り君",
    "message": "「那个……呃……」"
  },
  {
    "name": "凪",
    "message": "「同样的反应就不用再来一次了吧？」"
  },
  {
    "name": "凪",
    "message": "「…………」"
  },
  {
    "name": "小太り君",
    "message": "「那……不出去也可以吗……？」"
  },
  {
    "name": "凪",
    "message": "「呃，也许吧……不知道呢……」"
  },
  {
    "message": "我静静地等待，但门口没有任何要打开的迹象。"
  },
  {
    "message": "明明门是开着的，但感觉好害怕。"
  },
  {
    "name": "小太り君",
    "message": "「为什么要敲门呢，嗯，告诉我吧」"
  },
  {
    "name": "凪",
    "message": "「我也不知道啊……哈哈哈哈……」"
  },
  {
    "name": "凪",
    "message": "「也许你不想进来吧！」"
  },
  {
    "name": "凪",
    "message": "「对了！如果不想进来的话，就给门上锁吧！」"
  },
  {
    "name": "小太り君",
    "message": "「诶！？」"
  },
  {
    "name": "凪",
    "message": "「这只是以防万一哦，以防万一！」"
  },
  {
    "name": "小太り君",
    "message": "「啊啊啊啊，到底是怎么回事！？到底发生了什么！？」"
  },
  {
    "message": "小胖孩开始颤抖了…！"
  },
  {
    "message": "这种从外部施加的隐含压力，让人感到不安。"
  },
  {
    "message": "难道他真的是个机器人吗……这已经不知道是第几次有这种感觉了。"
  },
  {
    "message": "总之还是得打开门吧，也没有别的办法了……。"
  },
  {
    "message": "打开门，看到了今天一整天都很熟悉的少女站在那里。"
  },
  {
    "name": "凪",
    "message": "「哎呀呀，原来是菲布小姐啊……」"
  },
  {
    "message": "菲布小姐的太阳穴开始一跳一跳的，露出了一丝诡异的笑容。好可怕。"
  },
  {
    "name": "ファイブ",
    "message": "「这可不是这样的」"
  },
  {
    "name": "ファイブ",
    "message": "「你在做什么呢？」"
  },
  {
    "name": "凪",
    "message": "「什么啊，不就是在这里和小胖孩搞好关系嘛？」"
  },
  {
    "name": "ファイブ",
    "message": "「哼？连名字都不知道，你怎么能说出这种话呢？」"
  },
  {
    "name": "小太り君",
    "message": "「啊，虽然你帮了我，但我还没自我介绍呢。很抱歉。」"
  },
  {
    "name": "帝雄",
    "message": "「我的名字是成宫帝雄。」"
  },
  {
    "name": "凪",
    "message": "「哦，哦。很高兴认识你。」"
  },
  {
    "message": "……帝雄？真是个了不起的名字啊。"
  },
  {
    "name": "ファイブ",
    "message": "「呜哇！这种事情根本不重要啦！！」"
  },
  {
    "name": "凪",
    "message": "「呜哦哦哦！？」"
  },
  {
    "message": "狠狠地击中了我的肋部！！"
  },
  {
    "name": "帝雄",
    "message": "「啊啊啊啊啊！？」"
  },
  {
    "message": "我倒在了地上。"
  },
  {
    "name": "凪",
    "message": "「为什么，是我……？帝雄突然自我介绍，是因为…」"
  },
  {
    "name": "ファイブ",
    "message": "「不容置疑。连带责任。根源恶意，大清洗。」"
  },
  {
    "name": "凪",
    "message": "「呃啊」"
  },
  {
    "name": "ファイブ",
    "message": "「那么？你们真的只是在增进友谊而已吗？」"
  },
  {
    "message": "　"
  }
]