[
  {
    "name": "凪",
    "message": "「中午了！」"
  },
  {
    "message": "我被退学的事情终于平息下来了，上午的课也结束了。"
  },
  {
    "message": "我津津有味地享用着宿舍里最喜欢的三明治。"
  },
  {
    "name": "凪",
    "message": "「好美味啊……」"
  },
  {
    "message": "这一定是用上等小麦粉制作的面包，夹着新鲜的蔬菜。"
  },
  {
    "message": "这样的奢华在其他地方恐怕很难找到了，真是太棒了。"
  },
  {
    "name": "ファイブ",
    "message": "「非常抱歉，打扰了您的用餐。」"
  },
  {
    "name": "凪",
    "message": "「哦，菲布，你去哪里了？」"
  },
  {
    "message": "我在吃饭前去走廊看了看，但没有看到你的身影。"
  },
  {
    "name": "ファイブ",
    "message": "「我去了学生会室，想了解事情的经过。」"
  },
  {
    "name": "ファイブ",
    "message": "「说起来，你怎么能这么无所谓呢？你的胆子也太大了。」"
  },
  {
    "name": "凪",
    "message": "「哎呀，可是你也做得太过分了嘛。」"
  },
  {
    "name": "凪",
    "message": "「剩下的就交给你吧，我相信我未来的妻子。」"
  },
  {
    "name": "ファイブ",
    "message": "「是这样的。」"
  },
  {
    "name": "凪",
    "message": "「非常感谢你的冷漠！」"
  },
  {
    "name": "凪",
    "message": "「那么，结果如何？」"
  },
  {
    "name": "ファイブ",
    "message": "「凪先生的情况维持现状，会安排新的指导老师，让你等待通知。」"
  },
  {
    "name": "ファイブ",
    "message": "「至于狮童龙司，除了解职外，没有其他处罚。」"
  },
  {
    "name": "凪",
    "message": "「哦……」"
  },
  {
    "name": "ファイブ",
    "message": "「可以说是偏袒亲信了，这个裁决有些过于宽松了。」"
  },
  {
    "name": "凪",
    "message": "「是吗？我倒觉得这已经是很严厉的处罚了。」"
  },
  {
    "name": "凪",
    "message": "「龙司做了那样的事，周围人肯定会对他另眼相看。」"
  },
  {
    "name": "凪",
    "message": "「可即便如此，他还是不得不来学校，无处可逃，只能忍受接下来的日子。」"
  },
  {
    "name": "ファイブ",
    "message": "「原来如此……那干脆退学反而会轻松些。」"
  },
  {
    "name": "凪",
    "message": "「是这样的。」"
  },
  {
    "name": "凪",
    "message": "「那家伙看起来很有自尊心啊。可能会很难忍受吧。」"
  },
  {
    "name": "凪",
    "message": "（只希望他能真心反省就好了）"
  },
  {
    "message": "能否从明天起正常来校，还要看他本人的心志了。"
  },
  {
    "name": "凪",
    "message": "（或者……）"
  },
  {
    "name": "凪",
    "message": "（他肯定会记恨我。虽然报复心有些过了，不过还是要小心警惕）"
  },
  {
    "name": "凪",
    "message": "（要对可能发生的事情做好准备……）"
  },
  {
    "message": "单独来说，在目前的情况下，我在这个学校能做的事情并不多。"
  },
  {
    "name": "凪",
    "message": "（之后要给妇人打个电话。即便只是共享信息，也应该有一定价值吧）"
  },
  {
    "name": "ファイブ",
    "message": "「是啊。学校里，大家都在谈论凪先生的事情。甚至有人说，与凪先生扯上关系就会倒霉。」"
  },
  {
    "name": "凪",
    "message": "「我是恶魔吗？」"
  },
  {
    "name": "ファイブ",
    "message": "「有人说，学校里混进了一只凶暴的猛兽！」"
  },
  {
    "name": "凪",
    "message": "「抱歉，能不能别这么开心地说？」"
  },
  {
    "message": "菲布笑着示意，我只能无奈地挠挠头。"
  },
  {
    "name": "凪",
    "message": "「如果真有什么恶魔或猛兽般的力量，或许我会处理得更好。这次只是运气好而已。」"
  },
  {
    "name": "ファイブ",
    "message": "「说是运气好，似乎不太恰当。」"
  },
  {
    "name": "ファイブ",
    "message": "「离开学生会室时，在泰尔的衣服里装了手机，事情就按计划进行了呢？」"
  },
  {
    "name": "凪",
    "message": "「什么，你从哪里看到的？」"
  },
  {
    "name": "ファイブ",
    "message": "「我是自动机器人啊。」"
  },
  {
    "name": "凪",
    "message": "「啊，帝雄」"
  },
  {
    "name": "凪",
    "message": "「就交给我吧」"
  },
  {
    "name": "帝雄",
    "message": "「诶……」"
  },
  {
    "name": "凪",
    "message": "「我一定会救你的。一定会」"
  },
  {
    "name": "ファイブ",
    "message": "「她将一只手放在他的肩膀上，用有力的手势引导大家的视线，同时将手机悄悄塞进了他的衣服里」"
  },
  {
    "name": "ファイブ",
    "message": "「你那充满真诚的话语，并不像是在虚张声势。你一定是挑拨了那些说谎者的不安情绪」"
  },
  {
    "name": "ファイブ",
    "message": "「你没有采取任何行动，反而和我一起呆在房间里，这也是你的计策之一」"
  },
  {
    "name": "ファイブ",
    "message": "「因为看不见你在做什么，所以越发感到不安。这样就更容易露出马脚了」"
  },
  {
    "name": "ファイブ",
    "message": "「事实上，帝雄先生很快就被他们带走了，并受到了审问……」"
  },
  {
    "name": "凪",
    "message": "「我当时只能想到这个办法了。我确实做了对不起帝雄的事情」"
  },
  {
    "name": "ファイブ",
    "message": "「看来你是个相当有谋略的人啊」"
  },
  {
    "name": "凪",
    "message": "「这次只是运气好而已」"
  },
  {
    "name": "凪",
    "message": "「如果暴力的落脚点不对，手机就会被摔坏。如果龙司更加谨慎一些，结果可能会不一样」"
  },
  {
    "name": "ファイブ",
    "message": "「是不是预料到了帝雄先生的身体柔韧性，以及龙司先生这次行动的仓促？」"
  },
  {
    "name": "凪",
    "message": "「……我确实认为有胜算，所以才下了赌注」"
  },
  {
    "name": "ファイブ",
    "message": "「那就不要谦逊了。运气也是实力的一部分，要有自信哦」"
  },
  {
    "name": "凪",
    "message": "「嗯，是这样。……谢谢你，菲布」"
  },
  {
    "name": "？？？",
    "message": "「凪君……！」"
  },
  {
    "name": "凪",
    "message": "「哟，平安无事吗？」"
  },
  {
    "message": "为了调查的缘故，被学生会召唤的帝雄回来了。"
  },
  {
    "message": "在深夜回收手机时看到的，他那种有些释然的眼神依旧存在。"
  },
  {
    "name": "帝雄",
    "message": "「我把所有的事实都说了」"
  },
  {
    "name": "凪",
    "message": "「是吗是吗。有没有受到处罚？」"
  },
  {
    "name": "帝雄",
    "message": "「只是被警告了。他们说能理解情况」"
  },
  {
    "name": "帝雄",
    "message": "「都是凪的功劳，真的非常感谢你」"
  },
  {
    "name": "凪",
    "message": "「别放在心上」"
  },
  {
    "message": "亲切地看着我的帝雄，在第一节课结束后立刻来鞠躬道谢。"
  },
  {
    "message": "说是以恩报怨做出了这种行为。"
  },
  {
    "message": "所以，我只是简单地回了一句'别放在心上'。"
  },
  {
    "name": "帝雄",
    "message": "「你这个人啊……」"
  },
  {
    "name": "帝雄",
    "message": "「啊……那个……从现在开始，可以叫我凪君吗？」"
  },
  {
    "name": "帝雄",
    "message": "「我一向是用朋友的名字或昵称来称呼的」"
  },
  {
    "name": "帝雄",
    "message": "「作为亲近的印记……当然，前提是你愿意做我的朋友」"
  },
  {
    "name": "凪",
    "message": "「没问题，你不是刚才就这么叫我了吗？」"
  },
  {
    "name": "帝雄",
    "message": "「那个，那是我的感情先行了一步」"
  },
  {
    "name": "凪",
    "message": "「如果是可爱的女孩子说这种台词，那还有点意思，但从男生嘴里说出来就有点……」"
  },
  {
    "name": "帝雄",
    "message": "「那个……我会努力变得可爱的！」"
  },
  {
    "name": "凪",
    "message": "「别努力了！那是不可能的！」"
  },
  {
    "name": "凪",
    "message": "「对了帝雄，你最好离我远一点」"
  },
  {
    "name": "凪",
    "message": "「我似乎已经进化成恶魔或猛兽了」"
  },
  {
    "name": "ファイブ",
    "message": "「唔……」"
  },
  {
    "name": "凪",
    "message": "「喂，那边的人。别忍着笑啊」"
  },
  {
    "name": "帝雄",
    "message": "「……让我离你远一点，这话听起来好寂寞啊」"
  },
  {
    "name": "帝雄",
    "message": "「当时说这话的时候，我自己都没发现。所以我还是想成为凪君的朋友」"
  },
  {
    "name": "凪",
    "message": "「也许你会被别人欺负，还会被背后说坏话哦？」"
  },
  {
    "name": "帝雄",
    "message": "「不管别人怎么想，我都没关系。只要能回报凪君的恩情就好」"
  },
  {
    "name": "帝雄",
    "message": "「所以……虽然这话有点奇怪，但我希望你也能原谅龙司君」"
  },
  {
    "name": "帝雄",
    "message": "「作为交换，我会全力去弥补他的错误！」"
  },
  {
    "name": "凪",
    "message": "「即使被说要为男人奉献，我也不会高兴的。」"
  },
  {
    "name": "凪",
    "message": "「说起来，那家伙真是个幸运儿啊……」"
  },
  {
    "name": "帝雄",
    "message": "「因为是朋友嘛。」"
  },
  {
    "name": "凪",
    "message": "「你还是一如既往啊。」"
  },
  {
    "message": "即便被打，被贬低，被背叛。"
  },
  {
    "message": "但帝雄还是直视着对方。"
  },
  {
    "name": "凪",
    "message": "(这也是帝雄的优点所在，但对龙司来说也是一种负担。)"
  },
  {
    "name": "凪",
    "message": "「既然龙司什么也没做，那我也不会主动做什么。我保证。」"
  },
  {
    "name": "帝雄",
    "message": "「谢谢！那么……」"
  },
  {
    "name": "凪",
    "message": "「那就请多多关照了。」"
  },
  {
    "name": "帝雄",
    "message": "「我也是！」"
  },
  {
    "message": "我们再次握手致意。"
  },
  {
    "name": "帝雄",
    "message": "「对了凪，放学后有什么安排吗？」"
  },
  {
    "name": "凪",
    "message": "「大概会去综合图书馆学习吧。」"
  },
  {
    "name": "帝雄",
    "message": "「要不要来我部长的游戏部看看？」"
  },
  {
    "name": "凪",
    "message": "「游戏啊……听起来很有兴趣。」"
  },
  {
    "name": "帝雄",
    "message": "「你玩过什么？像是模拟器、Z Box还是换机器之类的？」"
  },
  {
    "name": "凪",
    "message": "「完全没玩过，我们珠贺良区娱乐项目很少。」"
  },
  {
    "name": "凪",
    "message": "「不如说我更多把时间用在生存上。」"
  },
  {
    "name": "帝雄",
    "message": "「原来如此……我很难想象你过得有多辛苦。」"
  },
  {
    "name": "凪",
    "message": "「说到娱乐的话，我和哥哥曾经一起看过一些色情杂志。」"
  },
  {
    "name": "帝雄",
    "message": "「色情……！？」"
  },
  {
    "name": "ファイブ",
    "message": "「……」"
  },
  {
    "name": "帝雄",
    "message": "「那个，你们是怎么弄到的？我很好奇。」"
  },
  {
    "name": "凪",
    "message": "「雷是个很擅长的妹妹呢。原案是我提供的，让她来制作。」"
  },
  {
    "name": "帝雄",
    "message": "「让妹妹来制作！？看起来做的很厉害啊。」"
  },
  {
    "name": "凪",
    "message": "「她也很投入地在做。和喜欢的人一起创作，才是最棒的吧？」"
  },
  {
    "name": "帝雄",
    "message": "「嗯，是这样没错，不过……有点背德的感觉。」"
  },
  {
    "name": "ファイブ",
    "message": "「……」"
  },
  {
    "name": "凪",
    "message": "「总之！做得越多，表现手法、分镜、构图等等就越有深度，嗯嗯。」"
  },
  {
    "name": "凪",
    "message": "「要是身边有会画画的人，男生肯定会去做色情杂志吧。」"
  },
  {
    "name": "帝雄",
    "message": "「呃，那个，我不太懂这方面的事情。」"
  },
  {
    "name": "凪",
    "message": "「那我就来教你色情杂志制作的好处吧！」"
  },
  {
    "name": "ファイブ",
    "message": "「不可以哦。」"
  },
  {
    "name": "凪",
    "message": "「等等！为什么菲布会否决掉！？」"
  },
  {
    "name": "ファイブ",
    "message": "「凪sama，如果只是你一个人的话我可以睁只眼闭只眼，但如果会对其他学生产生不良影响的话，那可就不好了。」"
  },
  {
    "name": "凪",
    "message": "「这不是什么不良影响啊！这是色情杂志！说白了就是保健教育嘛！」"
  },
  {
    "name": "帝雄",
    "message": "「……我虽然很感兴趣，但是还是算了吧。咽了口唾沫。」"
  },
  {
    "name": "ファイブ",
    "message": "「什么！？」"
  },
  {
    "name": "帝雄",
    "message": "「不，不用了！以后有机会再说吧，嗯嗯，有机会的话再说。」"
  },
  {
    "name": "ファイブ",
    "message": "「是的，那就好。」"
  },
  {
    "name": "凪",
    "message": "「真遗憾，但既然帝雄这么说，也没办法了。」"
  },
  {
    "name": "帝雄",
    "message": "「总之今天，我们去游乐区的'蜗牛'玩玩吧！」"
  },
  {
    "name": "帝雄",
    "message": "「尤其是那里的游戏，超级棒的。」"
  },
  {
    "name": "凪",
    "message": "「哦？你都这么说了，我还真期待起来了。」"
  },
  {
    "name": "凪",
    "message": "「不过啊帝雄，我有个严重的问题。」"
  },
  {
    "name": "凪",
    "message": "「我可没有那么多经济实力。真不好意思。」"
  },
  {
    "name": "帝雄",
    "message": "「那就由我来付你玩的费用吧，作为友谊的见证。」"
  },
  {
    "name": "凪",
    "message": "「好的！那就走吧！」"
  },
  {
    "name": "ファイブ",
    "message": "「真是个现金的家伙。」"
  },
  {
    "message": "但是既然别人愿意请客，我当然要收下啊！又不是我刻意要别人请客。"
  },
  {
    "name": "帝雄",
    "message": "「太棒了！那放学后我们一起去吧！」"
  },
  {
    "message": "一件事结束了，取而代之而来的是令人兴奋的话题，心情也跟着高涨起来。"
  },
  {
    "name": "凪",
    "message": "(既然龙司被免去了风纪委员长的职务，那我也自然就不再是他的下属了。)"
  },
  {
    "name": "凪",
    "message": "(在新的指导老师来之前，这段空白期正好可以好好享受一下。)"
  },
  {
    "message": "我来到这所学校，第一次和新认识的朋友们畅聊。"
  }
]